[
    {
        "Name": "LÊ HIỆU HỮU",
        "ID": "80248",
        "Department": "Bộ phận Kho"
    },
    {
        "Name": "THÁI THỊ HIẾU",
        "ID": "122560",
        "Department": "Bộ phận Kho"
    },
    {
        "Name": "ĐỖ VĂN TÌNH",
        "ID": "43282",
        "Department": "Bộ phận Kho"
    },
    {
        "Name": "ĐÀO THỊ HƯỜNG",
        "ID": "45765",
        "Department": "Bộ phận Kho"
    },
    {
        "Name": "LƯƠNG HỒNG MINH",
        "ID": "40757",
        "Department": "Bộ phận Kho"
    },
    {
        "Name": "NGUYỄN TUẤN LINH",
        "ID": "81860",
        "Department": "Bộ phận Kho"
    },
    {
        "Name": "TRỊNH TRỌNG HUY",
        "ID": "46102",
        "Department": "Bộ phận Kho"
    },
    {
        "Name": "LÊ THANH SANG",
        "ID": "47886",
        "Department": "Bộ phận Kho"
    },
    {
        "Name": "NGUYỄN THỊ XUYẾN",
        "ID": "83847",
        "Department": "Bộ phận Kho"
    },
    {
        "Name": "TRẦN THỊ VIỆT",
        "ID": "41554",
        "Department": "Bộ phận Kho"
    },
    {
        "Name": "NGUYỄN VĂN DƯƠNG",
        "ID": "44526",
        "Department": "Bộ phận Kho"
    },
    {
        "Name": "VÕ HOÀNG QUỐC TÚY",
        "ID": "92135",
        "Department": "Bộ phận Kho"
    },
    {
        "Name": "NGUYỄN THỊ LÝ",
        "ID": "77900",
        "Department": "Bộ phận Giám Định"
    },
    {
        "Name": "LÊ THỊ TRANG",
        "ID": "44665",
        "Department": "Bộ phận Giám Định"
    },
    {
        "Name": "VÕ THỊ TẤN",
        "ID": "80294",
        "Department": "Bộ phận Giám Định"
    },
    {
        "Name": "TRƯƠNG QUANG HIẾU",
        "ID": "82605",
        "Department": "Bộ phận Giám Định"
    },
    {
        "Name": "NGUYỄN THỊ THU THỦY",
        "ID": "111127",
        "Department": "Bộ phận IT",
        "Avatar": "111127.png"
    },
    {
        "Name": "NGUYỄN QUỐC DŨNG",
        "ID": "89482",
        "Department": "Bộ phận IT"
    },
    {
        "Name": "LÊ MINH HẰNG",
        "ID": "118478",
        "Department": "Bộ phận IT",
        "Avatar": "118478.jpg"
    },
    {
        "Name": "NGUYỄN ĐỨC THUẬN",
        "ID": "8023709",
        "Department": "Bộ phận IT"
    },
    {
        "Name": "NGUYỄN MINH TRƯỜNG",
        "ID": "114950",
        "Department": "Bộ phận IT"
    },
    {
        "Name": "CAO TRẦN ĐĂNG KHOA",
        "ID": "73699",
        "Department": "Bộ phận IT"
    },
    {
        "Name": "HOÀNG THỊ HỒNG PHƯỢNG",
        "ID": "111125",
        "Department": "Bộ phận IT",
        "Avatar": "111125.jpeg"
    },
    {
        "Name": "BÙI QUANG TIẾN",
        "ID": "46854",
        "Department": "Bộ phận IT"
    },
    {
        "Name": "NGUYỄN QUỐC HUỲNH",
        "ID": "121897",
        "Department": "Bộ phận IT"
    },
    {
        "Name": "LƯƠNG THỊ NGỌC NGA",
        "ID": "121488",
        "Department": "Bộ phận IT",
        "Avatar": "121488.JPEG"
    },
    {
        "Name": "NGUYỄN KỲ PHONG",
        "ID": "74162",
        "Department": "Bộ phận IT"
    },
    {
        "Name": "TRẦN VIỆT BẢO",
        "ID": "8024487",
        "Department": "Bộ phận IT"
    },
    {
        "Name": "NGUYỄN THỊ THỦY",
        "ID": "8023850",
        "Department": "Bộ phận IT",
        "Avatar": "8023850.jpg"
    },
    {
        "Name": "TRẦN THỊ THANH NGA",
        "ID": "44690",
        "Department": "Bộ phận IT",
        "Avatar": "44690.jpeg"
    },
    {
        "Name": "TRẦN QUỐC DƯỠNG",
        "ID": "104799",
        "Department": "Bộ phận IT"
    },
    {
        "Name": "UNG KHƯƠNG DUY",
        "ID": "98038",
        "Department": "Bộ phận IT"
    },
    {
        "Name": "VÕ ANH KHOA",
        "ID": "81007",
        "Department": "Bộ phận IT"
    },
    {
        "Name": "TRẦN THỊ MỸ PHỐ",
        "ID": "8019902",
        "Department": "Phòng TCKT-VTJ"
    },
    {
        "Name": "PHAN THỊ HẰNG",
        "ID": "8005611",
        "Department": "Phòng TCKT-VTJ"
    },
    {
        "Name": "ĐỒNG THỊ VI",
        "ID": "83742",
        "Department": "Phòng TCKT-VTJ"
    },
    {
        "Name": "NGÔ THỊ HỒNG YẾN",
        "ID": "8019889",
        "Department": "Phòng TCKT-VTJ"
    },
    {
        "Name": "NGUYỄN THỊ THANH NGA",
        "ID": "96523",
        "Department": "Phòng TCKT-VTJ"
    },
    {
        "Name": "ĐOÀN THỊ HỒNG PHÚC",
        "ID": "8007981",
        "Department": "Phòng TCKT-VTJ"
    },
    {
        "Name": "CHU THỊ HÀ",
        "ID": "117977",
        "Department": "Phòng TCKT"
    },
    {
        "Name": "KỲ THỊ ÁNH MINH",
        "ID": "41166",
        "Department": "Phòng TCKT"
    },
    {
        "Name": "NGUYỄN THỊ HUYỀN",
        "ID": "77183",
        "Department": "Phòng TCKT"
    },
    {
        "Name": "NGUYỄN THỊ NGỌC HUYỀN",
        "ID": "110459",
        "Department": "Phòng TCKT"
    },
    {
        "Name": "ĐÀO THỊ LAN PHƯƠNG",
        "ID": "120941",
        "Department": "Phòng TCKT"
    },
    {
        "Name": "NGUYỄN THỊ DUNG",
        "ID": "40312",
        "Department": "Phòng TCKT"
    },
    {
        "Name": "NGUYỄN THỊ THU",
        "ID": "111103",
        "Department": "Phòng TCKT"
    },
    {
        "Name": "NGUYỄN THỊ GIANG",
        "ID": "42562",
        "Department": "Phòng TCKT"
    },
    {
        "Name": "NGUYỄN THỊ THU PHƯƠNG",
        "ID": "9016",
        "Department": "Phòng TCKT"
    },
    {
        "Name": "LƯƠNG THỊ NGỌC HẰNG",
        "ID": "105358",
        "Department": "Phòng TCKT"
    },
    {
        "Name": "TRƯƠNG THỊ MAI THANH THỦY",
        "ID": "46995",
        "Department": "Phòng TCKT"
    },
    {
        "Name": "DƯƠNG THỊ BÍCH YẾN",
        "ID": "83172",
        "Department": "Phòng TCKT"
    },
    {
        "Name": "NGUYỄN THU HƯƠNG",
        "ID": "47060",
        "Department": "Phòng TCKT"
    },
    {
        "Name": "LÊ THỊ THU HUYỀN",
        "ID": "48795",
        "Department": "Phòng TCKT"
    },
    {
        "Name": "HOÀNG THỊ THỦY",
        "ID": "42623",
        "Department": "Phòng TCKT"
    },
    {
        "Name": "BÙI THỊ NGỌC",
        "ID": "50487",
        "Department": "Phòng TCKT"
    },
    {
        "Name": "NGUYỄN THỊ THANH HỒNG",
        "ID": "5987",
        "Department": "Phòng TCKT"
    },
    {
        "Name": "PHAN THỊ HƯỜNG",
        "ID": "83805",
        "Department": "Phòng TCKT"
    },
    {
        "Name": "TRẦN THỊ HỒNG HUỆ",
        "ID": "48796",
        "Department": "Phòng TCKT"
    },
    {
        "Name": "NGUYỄN THỊ TƯỜNG AN",
        "ID": 8022825,
        "Department": "Phòng TCKT"
    },
    {
        "Name": "PHAN THỊ VĨNH TOÀN",
        "ID": "117499",
        "Department": "Phòng Xuất nhập khẩu",
        "Avatar": "117499.jpg"
    },
    {
        "Name": "NGUYỄN THỊ HIỀN",
        "ID": "81006",
        "Department": "Phòng Xuất nhập khẩu",
        "Avatar": "81006.jpg"
    },
    {
        "Name": "PHAN THỊ NA",
        "ID": "73657",
        "Department": "Phòng Xuất nhập khẩu",
        "Avatar": "73657.jpg"
    },
    {
        "Name": "ĐỖ THU UYÊN",
        "ID": "8010678",
        "Department": "Phòng Xuất nhập khẩu",
        "Avatar": "8010678.jpg"
    },
    {
        "Name": "NGUYỄN VĂN SƠN",
        "ID": "120960",
        "Department": "Phòng Xuất nhập khẩu",
        "Avatar": "120960.jpg"
    },
    {
        "Name": "LƯƠNG THỊ CHUNG",
        "ID": "120700",
        "Department": "Phòng Xuất nhập khẩu",
        "Avatar": "120700.jpg"
    },
    {
        "Name": "NGUYỄN NGỌC VÂN ANH",
        "ID": "81935",
        "Department": "Phòng Xuất nhập khẩu",
        "Avatar": "81935.jpg"
    },
    {
        "Name": "PHAN THỊ THU VÂN",
        "ID": "117934",
        "Department": "Phòng Xuất nhập khẩu",
        "Avatar": "117934.jpg"
    },
    {
        "Name": "PHẠM THỊ MINH HUYỀN",
        "ID": "120980",
        "Department": "Phòng Xuất nhập khẩu",
        "Avatar": "120980.jpg"
    },
    {
        "Name": "MAI THỊ KIM NGÂN",
        "ID": "121487",
        "Department": "Phòng Xuất nhập khẩu",
        "Avatar": "121487.jpg"
    },
    {
        "Name": "DƯƠNG THANH TUẤN",
        "ID": "45425",
        "Department": "Phòng Xuất nhập khẩu",
        "Avatar": "45425.jpg"
    },
    {
        "Name": "HOÀNG NGUYỄN TỐ NHƯ",
        "ID": "8009259",
        "Department": "Phòng Xuất nhập khẩu",
        "Avatar": "8009259.jpg"
    },
    {
        "Name": "ĐOÀN NGUYỄN NGỌC ANH",
        "ID": "92982",
        "Department": "Phòng Xuất nhập khẩu",
        "Avatar": "92982.jpg"
    },
    {
        "Name": "NGUYỄN VĂN HỮU PHƯỚC",
        "ID": "93040",
        "Department": "Phòng Xuất nhập khẩu",
        "Avatar": "93040.jpg"
    },
    {
        "Name": "PHẠM THỊ NGỌC PHƯƠNG",
        "ID": "8008913",
        "Department": "Phòng Xuất nhập khẩu",
        "Avatar": "8008913.jpg"
    },
    {
        "Name": "TRẦN THỊ DIỆU HIỀN",
        "ID": "122077",
        "Department": "Phòng Xuất nhập khẩu",
        "Avatar": "122077.jpg"
    },
    {
        "Name": "NGUYỄN THỊ KIM CHI",
        "ID": "8013888",
        "Department": "Phòng Xuất nhập khẩu",
        "Avatar": "8013888.jpg"
    },
    {
        "Name": "MẠCH THỊ MI",
        "ID": "8024701",
        "Department": "Phòng Xuất nhập khẩu",
        "Avatar": "8024701.jpg"
    },
    {
        "Name": "PHẠM THỊ THANH THẾ",
        "ID": "85354",
        "Department": "Phòng Xuất nhập khẩu",
        "Avatar": "85354.jpg"
    },
    {
        "Name": "TRẦN ĐÀO THU THANH",
        "ID": "8019035",
        "Department": "Phòng Xuất nhập khẩu",
        "Avatar": "8019035.jpg"
    },
    {
        "Name": "ĐÀO THỊ DIỄM THẮM",
        "ID": "44708",
        "Department": "Phòng Xuất nhập khẩu",
        "Avatar": "44708.jpg"
    },
    {
        "Name": "PHẠM THỊ XUÂN MY",
        "ID": "8023775",
        "Department": "Phòng Xuất nhập khẩu",
        "Avatar": "8023775.jpg"
    },
    {
        "Name": "LÊ THỊ NGỌC LINH",
        "ID": "119102",
        "Department": "Phòng Xuất nhập khẩu",
        "Avatar": "119102.jpg"
    },
    {
        "Name": "TÔ KHẮC THIÊN",
        "ID": "86254",
        "Department": "Phòng Xuất nhập khẩu",
        "Avatar": "86254.jpg"
    },
    {
        "Name": "TRẦN QUANG THÀNH",
        "ID": "40174",
        "Department": "Phòng Xuất nhập khẩu",
        "Avatar": "40174.jpg"
    },
    {
        "Name": "LÊ THỊ HỒNG",
        "ID": "46798",
        "Department": "Phòng Xuất nhập khẩu",
        "Avatar": "46798.jpg"
    },
    {
        "Name": "LÊ THỊ THANH QUYÊN",
        "ID": "45544",
        "Department": "Phòng Xuất nhập khẩu",
        "Avatar": "45544.jpg"
    },
    {
        "Name": "ĐINH MINH ĐĂNG",
        "ID": "8008489",
        "Department": "Phòng Xuất nhập khẩu",
        "Avatar": "8008489.jpg"
    },
    {
        "Name": "TRƯƠNG HOÀI NGỌC CHÂU",
        "ID": "41179",
        "Department": "Phòng Xuất nhập khẩu",
        "Avatar": "41179.jpg"
    },
    {
        "Name": "NGÔ THỊ MAI HƯƠNG",
        "ID": "114671",
        "Department": "Phòng Xuất nhập khẩu",
        "Avatar": "114671.jpg"
    },
    {
        "Name": "ĐẶNG THỊ HỒNG UYÊN",
        "ID": "121246",
        "Department": "Phòng Xuất nhập khẩu",
        "Avatar": "121246.jpg"
    },
    {
        "Name": "PHAN THANH KHIẾT",
        "ID": "43455",
        "Department": "Phòng Xuất nhập khẩu",
        "Avatar": "43455.jpg"
    },
    {
        "Name": "NGUYỄN MINH PHƯỚC",
        "ID": "40720",
        "Department": "Phòng Xuất nhập khẩu",
        "Avatar": "40720.jpg"
    },
    {
        "Name": "CHỊ NGUYỄN THÚY PHƯỢNG",
        "ID": "VCB01",
        "Department": "Khách mời",
        "Avatar": "VCB01.jpg"
    },
    {
        "Name": "CHỊ NGUYỄN NHẬT QUANG",
        "ID": "VCB02",
        "Department": "Khách mời",
        "Avatar": "VCB02.jpg"
    },
    {
        "Name": "CHỊ DƯƠNG NGUYỄN TRÚC NHI",
        "ID": "VCB03",
        "Department": "Khách mời",
        "Avatar": "VCB03.jpg"
    },
    {
        "Name": "ANH TRẦN CHÁNH TRỰC",
        "ID": "VCB04",
        "Department": "Khách mời",
        "Avatar": "VCB04.jpg"
    },
    {
        "Name": "ANH HÀ MẠNH LINH",
        "ID": "VCB05",
        "Department": "Khách mời",
        "Avatar": "VCB05.jpg"
    },
    {
        "Name": "ANH TRẦN TRÚC PHƯƠNG",
        "ID": "VCB06",
        "Department": "Khách mời",
        "Avatar": "VCB06.jpg"
    },
    {
        "Name": "ANH CAO TẤT THẮNG",
        "ID": "VCB07",
        "Department": "Khách mời",
        "Avatar": "VCB07.jpg"
    }
]